pyfmrheo/__init__.py
pyfmrheo/models/__init__.py
pyfmrheo/models/bec.py
pyfmrheo/models/calibration.py
pyfmrheo/models/double_powerlaw.py
pyfmrheo/models/drag_sphere_model.py
pyfmrheo/models/geom_coeffs.py
pyfmrheo/models/hertz.py
pyfmrheo/models/rheology.py
pyfmrheo/models/sader.py
pyfmrheo/models/sho.py
pyfmrheo/models/sine.py
pyfmrheo/models/ting.py
pyfmrheo/routines/HertzFit.py
pyfmrheo/routines/MicrorheologyFFT.py
pyfmrheo/routines/MicrorheologySine.py
pyfmrheo/routines/NonContactCal.py
pyfmrheo/routines/PiezoCharacterization.py
pyfmrheo/routines/TingFit.py
pyfmrheo/routines/ViscousDragSteps.py
pyfmrheo/routines/__init__.py
pyfmrheo/utils/__init__.py
pyfmrheo/utils/force_curves.py
pyfmrheo/utils/signal_processing.py
pyfmrheo-0.1.3.dist-info/LICENSE
pyfmrheo-0.1.3.dist-info/METADATA
pyfmrheo-0.1.3.dist-info/WHEEL
pyfmrheo-0.1.3.dist-info/top_level.txt
pyfmrheo-0.1.3.dist-info/RECORD
