Metadata-Version: 2.1
Name: pyfmrheo
Version: 0.1.3
Summary: A python package to perform analysis of Force Microscopy data.
Home-page: https://github.com/jlopezalo/PyFMRheo
Author: Javier Lopez Alonso
Author-email: jla.lopez.18@gmail.com
Project-URL: Bug Tracker, https://github.com/jlopezalo/PyFMRheo/issues
Project-URL: repository, https://github.com/jlopezalo/PyFMRheo
Classifier: Programming Language :: Python :: 3
Classifier: License :: OSI Approved :: MIT License
Classifier: Operating System :: OS Independent
Requires-Python: >=3.6
License-File: LICENSE
Requires-Dist: numpy
Requires-Dist: scipy
Requires-Dist: lmfit
Requires-Dist: pyfmreader
Requires-Dist: requests
